ltamp/__init__.py
ltamp/hidDevice.py
ltamp/hidWrapper.py
ltamp/ltAmpAsync.py
ltamp/ltAmpBase.py
ltamp/ltAmpSync.py
ltamp/protocol/ActiveDisplay_pb2.py
ltamp/protocol/AudioStatus_pb2.py
ltamp/protocol/AuditionPresetStatus_pb2.py
ltamp/protocol/AuditionPreset_pb2.py
ltamp/protocol/AuditionStateRequest_pb2.py
ltamp/protocol/AuditionStateStatus_pb2.py
ltamp/protocol/ClearPresetStatus_pb2.py
ltamp/protocol/ClearPreset_pb2.py
ltamp/protocol/ConnectionStatusRequest_pb2.py
ltamp/protocol/ConnectionStatus_pb2.py
ltamp/protocol/CurrentDisplayedPresetIndexStatus_pb2.py
ltamp/protocol/CurrentLoadedPresetIndexBypassStatus_pb2.py
ltamp/protocol/CurrentLoadedPresetIndexStatus_pb2.py
ltamp/protocol/CurrentPresetRequest_pb2.py
ltamp/protocol/CurrentPresetSet_pb2.py
ltamp/protocol/CurrentPresetStatus_pb2.py
ltamp/protocol/DspUnitParameterStatus_pb2.py
ltamp/protocol/ExitAuditionPresetStatus_pb2.py
ltamp/protocol/ExitAuditionPreset_pb2.py
ltamp/protocol/FenderMessageLT_pb2.py
ltamp/protocol/FirmwareVersionRequest_pb2.py
ltamp/protocol/FirmwareVersionStatus_pb2.py
ltamp/protocol/FrameBufferMessageRequest_pb2.py
ltamp/protocol/FrameBufferMessage_pb2.py
ltamp/protocol/Heartbeat_pb2.py
ltamp/protocol/IndexButton_pb2.py
ltamp/protocol/IndexEncoder_pb2.py
ltamp/protocol/IndexPot_pb2.py
ltamp/protocol/LT4FootswitchModeRequest_pb2.py
ltamp/protocol/LT4FootswitchModeStatus_pb2.py
ltamp/protocol/LineOutGainRequest_pb2.py
ltamp/protocol/LineOutGainSet_pb2.py
ltamp/protocol/LineOutGainStatus_pb2.py
ltamp/protocol/LoadPreset_TestSuite_pb2.py
ltamp/protocol/LoadPreset_pb2.py
ltamp/protocol/LoopbackTest_pb2.py
ltamp/protocol/MemoryUsageRequest_pb2.py
ltamp/protocol/MemoryUsageStatus_pb2.py
ltamp/protocol/ModalStatusMessage_pb2.py
ltamp/protocol/NewPresetSavedStatus_pb2.py
ltamp/protocol/PresetJSONMessageRequest_LT_pb2.py
ltamp/protocol/PresetJSONMessage_pb2.py
ltamp/protocol/PresetSavedStatus_pb2.py
ltamp/protocol/ProcessorUtilizationRequest_pb2.py
ltamp/protocol/ProcessorUtilization_pb2.py
ltamp-0.2.7.dist-info/licenses/LICENSE
ltamp-0.2.7.dist-info/METADATA
ltamp-0.2.7.dist-info/WHEEL
ltamp-0.2.7.dist-info/top_level.txt
ltamp-0.2.7.dist-info/RECORD
