Metadata-Version: 2.4
Name: ltamp
Version: 0.2.7
Summary: 🎸 Cross-platform python interface for LT guitar/bass amplifiers
License: MIT
Project-URL: Homepage, https://github.com/bendertools/LtAmp.py
Project-URL: Repository, https://github.com/bendertools/LtAmp.py
Classifier: Programming Language :: Python :: 3
Classifier: Programming Language :: Python :: 3.8
Classifier: Programming Language :: Python :: 3.9
Classifier: Programming Language :: Python :: 3.10
Classifier: Programming Language :: Python :: 3.11
Classifier: Programming Language :: Python :: 3.12
Classifier: Operating System :: OS Independent
Classifier: Development Status :: 3 - Alpha
Classifier: Topic :: Software Development :: Libraries :: Python Modules
Classifier: Topic :: System :: Hardware :: Universal Serial Bus (USB)
Classifier: Topic :: Artistic Software
Classifier: License :: OSI Approved :: MIT License
Requires-Python: >=3.8
License-File: LICENSE
Requires-Dist: protobuf>=5.0.0
Requires-Dist: hidapi; sys_platform != "win32"
Requires-Dist: pywinusb; sys_platform == "win32"
Dynamic: license-file
